setup.py
weathers/__init__.py
weathers/api.py
weathers/city_id.py
weathers/util.py
weathers/weather.py
weathers.egg-info/PKG-INFO
weathers.egg-info/SOURCES.txt
weathers.egg-info/dependency_links.txt
weathers.egg-info/requires.txt
weathers.egg-info/top_level.txt