Metadata-Version: 1.1
Name: weathers
Version: 1.2.1
Summary: A sample Python project to make configuration  easy
Home-page: https://github.com/510908220/easyconfig.git
Author: HuZhongZhong
Author-email: 510908220@qq.com
License: MIT
Keywords: configuration
Platform: UNKNOWN
Classifier: Development Status :: 3 - Alpha
Classifier: Intended Audience :: Developers
Classifier: Topic :: Software Development :: Build Tools
Classifier: License :: OSI Approved :: MIT License
Classifier: Programming Language :: Python :: 3
Classifier: Programming Language :: Python :: 3.2
Classifier: Programming Language :: Python :: 3.3
Classifier: Programming Language :: Python :: 3.4
